[
    {
        "id": "23f5e0b0",
        "tweet_text": "\ud83d\udea8 HUGE NEWS: Tottenham is in final negotiations for Roberto De Zerbi to become their new manager after parting ways with Igor Tudor! The club aims to turn their season around. \u26bd\ufe0f\ud83d\udd25 #THFC #DeZerbi",
        "source_url": "https://www.mirror.co.uk/sport/football/news/tottenham-de-zerbi-next-manager-36945800",
        "article_title": "Tottenham's mega contract offer to Roberto De Zerbi with final negotiations underway",
        "created_at": "2026-03-30T18:51:30.523869",
        "scheduled_for": null,
        "expires_at": "2026-03-30T22:51:30.523869",
        "type": "manual",
        "status": "pending"
    },
    {
        "id": "295bd388",
        "tweet_text": "\ud83d\udea8 Tottenham are in advanced talks to appoint Roberto De Zerbi as their new manager! The club aims to secure him on a long-term deal, making him their only candidate. #THFC #DeZerbi",
        "source_url": "https://www.theguardian.com/football/2026/mar/30/roberto-de-zerbi-igor-tudor-tottenham-new-manager",
        "article_title": "Tottenham close to appointing Roberto De Zerbi as new manager after talks",
        "created_at": "2026-03-30T19:51:21.221893",
        "scheduled_for": null,
        "expires_at": "2026-03-30T23:51:21.221893",
        "type": "manual",
        "status": "pending"
    },
    {
        "id": "c16b2877",
        "tweet_text": "\ud83d\udea8 HUGE NEWS: Tottenham are in advanced talks to appoint Roberto De Zerbi as their new manager, aiming to secure their place in the Premier League! \u26bd\ufe0f #TottenhamHotspur #DeZerbi",
        "source_url": "https://www.mirror.co.uk/sport/football/news/roberto-de-zerbi-tottenham-spurs-36945729",
        "article_title": "Roberto De Zerbi's sudden change of heart says everything about Tottenham's top target",
        "created_at": "2026-03-30T19:51:30.271165",
        "scheduled_for": null,
        "expires_at": "2026-03-30T23:51:30.271165",
        "type": "manual",
        "status": "pending"
    },
    {
        "id": "8d94dfd3",
        "tweet_text": "\ud83d\udea8 DR Congo faces Jamaica in a crucial World Cup playoff, aiming to end a 52-year drought since their last appearance in 1974. A historic moment for Congolese football! \ud83c\udde8\ud83c\udde9\u26bd #WorldCup2026 #DRCongo",
        "source_url": "https://www.bbc.com/sport/football/articles/cwyd1zpy81mo?at_medium=RSS&at_campaign=rss",
        "article_title": "'This is bigger than football' - DR Congo bid to end 52-year World Cup wait",
        "created_at": "2026-03-30T20:37:37.681186",
        "scheduled_for": null,
        "expires_at": "2026-03-31T00:37:37.681186",
        "type": "manual",
        "status": "pending"
    },
    {
        "id": "45517719",
        "tweet_text": "\ud83d\udea8 Tottenham set to appoint Roberto De Zerbi as their new manager, putting to rest rumors of Mauricio Pochettino's return! Exciting times ahead for Spurs! \u26bd\ufe0f\ud83d\udd1c #THFC #DeZerbi",
        "source_url": "https://www.mirror.co.uk/sport/football/news/mauricio-pochettino-tottenham-spurs-usa-36945945",
        "article_title": "Mauricio Pochettino issues update as Tottenham close in on appointing next manager",
        "created_at": "2026-03-30T20:37:44.766585",
        "scheduled_for": null,
        "expires_at": "2026-03-31T00:37:44.766585",
        "type": "manual",
        "status": "pending"
    },
    {
        "id": "d6fbbf4a",
        "tweet_text": "\ud83d\udea8 BREAKING: A French court has dismissed Cardiff City's \u00a3106m claim against Nantes over Emiliano Sala's tragic death in a 2019 plane crash. This follows multiple rulings against Cardiff in the ongoing legal battle. \u2696\ufe0f\ud83d\udc94 #CardiffCity #EmilianoSala",
        "source_url": "https://www.theguardian.com/football/2026/mar/30/court-dismisses-cardiff-claim-against-nantes-emiliano-sala-death",
        "article_title": "Court dismisses Cardiff\u2019s \u00a3106m claim against Nantes over Emiliano Sala\u2019s death",
        "created_at": "2026-03-30T21:35:30.515786",
        "scheduled_for": "2026-03-30T21:45:30.515786",
        "expires_at": "2026-03-30T22:35:30.515786",
        "type": "auto",
        "status": "pending"
    },
    {
        "id": "a6b247a5",
        "tweet_text": "\ud83d\udea8 HUGE NEWS: Tottenham is in advanced talks to hire Roberto De Zerbi as their new manager after Igor Tudor's exit. Lewis Dunk warns of a tough transition ahead! \u26bd\ufe0f\ud83d\udd25 #Tottenham #DeZerbi",
        "source_url": "https://www.mirror.co.uk/sport/football/news/tottenham-next-manager-de-zerbi-36946231",
        "article_title": "'I worked with Tottenham target Roberto De Zerbi - the first few weeks were horrendous'",
        "created_at": "2026-03-30T21:35:33.618469",
        "scheduled_for": null,
        "expires_at": "2026-03-31T01:35:33.618469",
        "type": "manual",
        "status": "pending"
    },
    {
        "id": "704cbcd8",
        "tweet_text": "\ud83d\udea8 HUGE NEWS: Tottenham Hotspur are in advanced talks with Roberto De Zerbi to become their new manager, with the ex-Brighton boss ready to take charge immediately! \u26bd\ufe0f\ud83d\udd04 #THFC #DeZerbi",
        "source_url": "https://www.bbc.com/sport/football/articles/cq59wed70v5o?at_medium=RSS&at_campaign=rss",
        "article_title": "De Zerbi in advanced talks to become Spurs manager",
        "created_at": "2026-03-30T22:27:37.143112",
        "scheduled_for": null,
        "expires_at": "2026-03-31T02:27:37.143112",
        "type": "manual",
        "status": "pending"
    },
    {
        "id": "e33ea96c",
        "tweet_text": "\ud83d\udea8 HUGE NEWS: Italy's World Cup play-off clash with Bosnia is marred by a spy-gate scandal, as Bosnia accuses Italy of sending a spy to observe them. The tension builds! \ud83c\uddee\ud83c\uddf9\ud83c\udde7\ud83c\udde6 #WorldCup #SpyGate",
        "source_url": "https://www.mirror.co.uk/sport/football/news/bosnia-italy-spy-world-cup-36946320",
        "article_title": "Italy in World Cup spy-gate row as Bosnia fire accusation at them after soldier spotted",
        "created_at": "2026-03-30T22:27:42.425721",
        "scheduled_for": null,
        "expires_at": "2026-03-31T02:27:42.425721",
        "type": "manual",
        "status": "pending"
    },
    {
        "id": "fca7dd36",
        "tweet_text": "\ud83d\udea8 Bernardo Silva hints at leaving Manchester City as his contract nears its end! The midfielder's future is uncertain ahead of the crucial title clash with Arsenal. \u26bd\ufe0f\ud83d\udd0d #ManCity #PremierLeague",
        "source_url": "https://www.mirror.co.uk/sport/football/transfer-news/bernardo-silva-manchester-city-arsenal-36946193",
        "article_title": "Bernardo Silva drops Man City exit bombshell ahead of Arsenal title battle",
        "created_at": "2026-03-30T22:27:44.491023",
        "scheduled_for": null,
        "expires_at": "2026-03-31T02:27:44.491023",
        "type": "manual",
        "status": "pending"
    }
]