[
    {
        "id": "5c060224",
        "tweet_text": "\ud83d\udea8 Bayern Munich take a crucial 3-2 lead over Manchester United in the Women's Champions League quarter-finals, thanks to a brace from Pernille Harder! \u26bd\ufe0f\ud83d\udd25 #WCL #BayernMunich",
        "source_url": "https://www.skysports.com/football/manchester-united-women-vs-bayern-munich-women/report/551339",
        "article_title": "Classy Bayern earn WCL QF first-leg advantage over Man Utd",
        "created_at": "2026-03-26T06:59:52.332370",
        "scheduled_for": null,
        "expires_at": "2026-03-26T10:59:52.332370",
        "type": "manual",
        "status": "pending"
    },
    {
        "id": "bcd4c323",
        "tweet_text": "\ud83d\udea8 HUGE NEWS: Rangers chairman Andrew Cavenagh confirms a \u00a316m cash boost for summer transfers and club improvements! \ud83d\udcb0\u26bd #RangersFC #TransferNews",
        "source_url": "https://www.skysports.com/football/news/12040/13524380/rangers-qa-on-16m-share-issue-transfer-plans-old-firm-fan-clash-future-celtic-park-ticket-allocations-var-referee-summit-and-more",
        "article_title": "Rangers' \u00a316m transfer boost, Old Firm away tickets latest & VAR ref summit",
        "created_at": "2026-03-26T06:59:55.515949",
        "scheduled_for": null,
        "expires_at": "2026-03-26T10:59:55.515949",
        "type": "manual",
        "status": "pending"
    },
    {
        "id": "7a71a161",
        "tweet_text": "\ud83d\udea8 Everton to challenge Premier League over lack of sanctions against Chelsea for rule breaches, demanding formal explanation after Chelsea faced no penalties. \u2696\ufe0f #Everton #Chelsea",
        "source_url": "https://www.theguardian.com/football/2026/mar/25/everton-exploring-legal-options-over-lack-sporting-sanctions-against-chelsea",
        "article_title": "Everton exploring legal options over lack of sporting sanctions against Chelsea",
        "created_at": "2026-03-26T07:00:02.444546",
        "scheduled_for": null,
        "expires_at": "2026-03-26T11:00:02.444546",
        "type": "manual",
        "status": "pending"
    },
    {
        "id": "367c264a",
        "tweet_text": "\ud83d\udea8 Harry Maguire bounces back to the England squad after three tough years at Manchester United! He's now eyeing a spot in the World Cup. Can he reclaim his place? \ud83c\uddec\ud83c\udde7\u26bd #ThreeLions #WorldCup2026",
        "source_url": "https://www.mirror.co.uk/sport/football/news/harry-maguire-feared-england-career-36921684",
        "article_title": "Harry Maguire feared his England career was over - now he's ready for World Cup fight",
        "created_at": "2026-03-26T08:04:44.252304",
        "scheduled_for": null,
        "expires_at": "2026-03-26T12:04:44.252304",
        "type": "manual",
        "status": "pending"
    }
]